{"cards":[{"id":"lonelymod:CommandDestroy","name":"Command: Destroy","color":"Colorless","rarity":"Special","type":"Skill","cost":"0","description":"Retain.\nlonelymod:Call lonelymod:Attack.\n~~- Exhaust. -~~ ","mod":"LonelyMod"},{"id":"lonelymod:FeedTheBear","name":"Feed The Bear","color":"Colorless","rarity":"Special","type":"Skill","cost":"1","description":"Give him some energy.\nPlay as much as you like.","mod":"LonelyMod"},{"id":"lonelymod:GodlyPowers","name":"Godly Powers","color":"Colorless","rarity":"Special","type":"Skill","cost":"0","description":" (Retain.)\nGain [E].\nlonelymod:Return.","mod":"LonelyMod"},{"id":"lonelymod:TheDrybear","name":"The Drybear","color":"Colorless","rarity":"Special","type":"Skill","cost":"0","description":"lonelymod:Companion.\nA full stomach doesn't stop him from chomping down everything that fits in his mouth.","mod":"LonelyMod"},{"id":"lonelymod:TheDryhound","name":"The Dryhound","color":"Colorless","rarity":"Special","type":"Skill","cost":"0","description":"lonelymod:Companion.\nAn emaciated canine from the Drywoods, he's always hungry.","mod":"LonelyMod"},{"id":"lonelymod:TheManiac","name":"The Maniac","color":"Colorless","rarity":"Special","type":"Skill","cost":"0","description":"lonelymod:Companion.\nA vicious gremlin that becomes angrier whenever its friend is hurt.","mod":"LonelyMod"},{"id":"lonelymod:TheMechanic","name":"The Mechanic","color":"Colorless","rarity":"Special","type":"Skill","cost":"0","description":"lonelymod:Companion.\nAn inventive gremlin that has spent its life tinkering with Orb technology.","mod":"LonelyMod"},{"id":"lonelymod:TheOracle","name":"The Oracle","color":"Colorless","rarity":"Special","type":"Skill","cost":"0","description":"lonelymod:Companion.\nA wise gremlin that prefers a patient approach to combat.","mod":"LonelyMod"},{"id":"lonelymod:TheOutcast","name":"The Outcast","color":"Colorless","rarity":"Special","type":"Skill","cost":"0","description":"lonelymod:Companion.\nAn unwanted gremlin that tries its best to help out.","mod":"LonelyMod"},{"id":"lonelymod:TheSpy","name":"The Spy","color":"Colorless","rarity":"Special","type":"Skill","cost":"0","description":"lonelymod:Companion.\nA deadly gremlin that can use anything you give it to great effect.","mod":"LonelyMod"},{"id":"lonelymod:TheVulchyr","name":"The Vulchyr","color":"Colorless","rarity":"Special","type":"Skill","cost":"0","description":"lonelymod:Companion.\nAn evil being that drains power from its master to destroy their enemies.","mod":"LonelyMod"},{"id":"lonelymod:CommandAttack","name":"Command: Attack","color":"Colorless","rarity":"Uncommon","type":"Attack","cost":"1","description":"Deal 6 (9) damage.\nlonelymod:Call lonelymod:Attack.","mod":"LonelyMod"},{"id":"lonelymod:CommandProtect","name":"Command: Protect","color":"Colorless","rarity":"Uncommon","type":"Skill","cost":"1","description":"Gain 5 (8) Block.\nlonelymod:Call lonelymod:Protect.","mod":"LonelyMod"},{"id":"lonelymod:CommandSpecial","name":"Command: Special","color":"Colorless","rarity":"Uncommon","type":"Skill","cost":"2 (1)","description":"lonelymod:Call lonelymod:Special.\nExhaust.","mod":"LonelyMod"},{"id":"lonelymod:CommandCopy","name":"Command: Copy","color":"Colorless","rarity":"Rare","type":"Skill","cost":"1","description":"If the last card played this combat was:\nAn Attack, lonelymod:Call lonelymod:Attack.\nA Skill, lonelymod:Call lonelymod:Protect. (A Power, lonelymod:Call lonelymod:Special.)\n","mod":"LonelyMod"},{"id":"lonelymod:CommandTarget","name":"Command: Target","color":"Colorless","rarity":"Rare","type":"Skill","cost":"1","description":"Apply 3 lonelymod:Target.\nlonelymod:Call lonelymod:Protect.\nAdd 1 Command: Destroy (+) to your hand.","mod":"LonelyMod"},{"id":"lonelymod:Defend","name":"Defend","color":"Lonely_yellow","rarity":"Basic","type":"Skill","cost":"1","description":"Gain 5 (8) Block.","mod":"LonelyMod"},{"id":"lonelymod:Heel","name":"Heel!","color":"Lonely_yellow","rarity":"Basic","type":"Attack","cost":"2","description":"Deal 10 (14) damage.\nlonelymod:Call lonelymod:Protect.","mod":"LonelyMod"},{"id":"lonelymod:Sic","name":"Sic!","color":"Lonely_yellow","rarity":"Basic","type":"Skill","cost":"1","description":" (Apply 1) lonelymod: (Target to a random enemy.lonelymod:)\nCall lonelymod:Attack.","mod":"LonelyMod"},{"id":"lonelymod:Strike","name":"Strike","color":"Lonely_yellow","rarity":"Basic","type":"Attack","cost":"1","description":"Deal 6 (9) damage.","mod":"LonelyMod"},{"id":"lonelymod:ActionPlan","name":"Action Plan","color":"Lonely_yellow","rarity":"Common","type":"Skill","cost":"2","description":"Gain 8 (10) Block.\nlonelymod:Call lonelymod:Protect.\nNext turn, lonelymod:Call lonelymod:Attack (and draw 1 card).","mod":"LonelyMod"},{"id":"lonelymod:Adapt","name":"Adapt","color":"Lonely_yellow","rarity":"Common","type":"Skill","cost":"1","description":"Gain 5 (7) Block.\nDraw 1 card.\nIf you play the drawn card this turn, gain 5 (7) Block.","mod":"LonelyMod"},{"id":"lonelymod:DeviousPloy","name":"Devious Ploy","color":"Lonely_yellow","rarity":"Common","type":"Attack","cost":"1","description":"Deal 7 (10) damage.\nlonelymod:Plan 2 (3).\nNext turn, Gain [E].","mod":"LonelyMod"},{"id":"lonelymod:Distracted","name":"Distracted","color":"Lonely_yellow","rarity":"Common","type":"Skill","cost":"0","description":"Gain 4 (7) Vigor.\nNext turn, lose [E] and add an Overreaction to your hand.","mod":"LonelyMod"},{"id":"lonelymod:Forgetful","name":"Forgetful","color":"Lonely_yellow","rarity":"Common","type":"Skill","cost":"0","description":"Gain 3 (6) lonelymod:Stamina.\nNext turn, draw 1 less card and add a Panic Attack to your hand.","mod":"LonelyMod"},{"id":"lonelymod:Help","name":"Help!","color":"Lonely_yellow","rarity":"Common","type":"Skill","cost":"1","description":"At the end of your next 2 (3) turns, lonelymod:Call lonelymod:Protect.","mod":"LonelyMod"},{"id":"lonelymod:Kill","name":"Kill!","color":"Lonely_yellow","rarity":"Common","type":"Attack","cost":"2","description":"Deal 10 (15) damage.\nlonelymod:Call lonelymod:Attack.\nAt the start of your next 2 turns, lonelymod:Call lonelymod:Attack.","mod":"LonelyMod"},{"id":"lonelymod:LongShot","name":"Long Shot","color":"Lonely_yellow","rarity":"Common","type":"Attack","cost":"1","description":"Deal 7 (9) damage. Deal 5 (7) more damage if played on the furthest away enemy.","mod":"LonelyMod"},{"id":"lonelymod:Marker","name":"Marker","color":"Lonely_yellow","rarity":"Common","type":"Attack","cost":"1","description":"Deal 8 (11) damage.\nApply 2 (3) lonelymod:Target.","mod":"LonelyMod"},{"id":"lonelymod:OccultPractice","name":"Occult Practice","color":"Lonely_yellow","rarity":"Common","type":"Skill","cost":"1","description":"Gain 7 (10) Strength this turn.\nShuffle 2 Wounds into your draw pile.\nExhaust.","mod":"LonelyMod"},{"id":"lonelymod:Overpower","name":"Overpower","color":"Lonely_yellow","rarity":"Common","type":"Skill","cost":"1","description":"Gain 8 (10) Block.\nIf the enemy intends to deal less damage than your Block, apply 2 (3) Weak.","mod":"LonelyMod"},{"id":"lonelymod:Overthrow","name":"Overthrow","color":"Lonely_yellow","rarity":"Common","type":"Attack","cost":"1","description":"Deal 9 (11) Damage.\nIf you have no energy, apply 2 (3) Vulnerable.","mod":"LonelyMod"},{"id":"lonelymod:PincerAttack","name":"Pincer Attack","color":"Lonely_yellow","rarity":"Common","type":"Attack","cost":"1","description":"Deal 8 (10) damage.\nIf your lonelymod:Companion intends to lonelymod:Attack, deal 8 (10) damage again.","mod":"LonelyMod"},{"id":"lonelymod:PlannedAssault","name":"Planned Assault","color":"Lonely_yellow","rarity":"Common","type":"Attack","cost":"0","description":"Deal 4 (6) damage.\nWhenever you lonelymod:Plan, move this card from the draw pile to your hand.","mod":"LonelyMod"},{"id":"lonelymod:PureSkill","name":"Pure Skill","color":"Lonely_yellow","rarity":"Common","type":"Skill","cost":"0","description":"Gain 3 (4) Vigor.\nGain 2 (3) lonelymod:Stamina.\nlonelymod:Plan 1 (2).","mod":"LonelyMod"},{"id":"lonelymod:Siphon","name":"Siphon","color":"Lonely_yellow","rarity":"Common","type":"Attack","cost":"1","description":"Deal 5 (7) damage.\nGain Vigor equal to the unblocked damage dealt.","mod":"LonelyMod"},{"id":"lonelymod:StandStrong","name":"Stand Strong","color":"Lonely_yellow","rarity":"Common","type":"Skill","cost":"1","description":"Gain 7 (10) Block.\nlonelymod:Return.","mod":"LonelyMod"},{"id":"lonelymod:StrikeBack","name":"Strike Back","color":"Lonely_yellow","rarity":"Common","type":"Attack","cost":"1","description":"Deal 8 (12) damage.\nIf you have a debuff, gain [E].","mod":"LonelyMod"},{"id":"lonelymod:Volley","name":"Volley","color":"Lonely_yellow","rarity":"Common","type":"Attack","cost":"1","description":"Deal 6 (9) damage to ALL enemies.\nlonelymod:Return.","mod":"LonelyMod"},{"id":"lonelymod:Brainstorm","name":"Brainstorm","color":"Lonely_yellow","rarity":"Uncommon","type":"Attack","cost":"2","description":"Deal 13 (17) damage to ALL enemies.\nChoose a card in your discard pile to lonelymod:Return.","mod":"LonelyMod"},{"id":"lonelymod:BrokenDreams","name":"Broken Dreams","color":"Lonely_yellow","rarity":"Uncommon","type":"Skill","cost":"0","description":"Shuffle a Misery into your draw pile.\nDraw 2 (3) cards.\nGain 3 Weak.","mod":"LonelyMod"},{"id":"lonelymod:BrokenHeart","name":"Broken Heart","color":"Lonely_yellow","rarity":"Uncommon","type":"Skill","cost":"0","description":"Add an Outburst to your hand.\nGain [E] [E] [E].\nGain 3 (2) Vulnerable.","mod":"LonelyMod"},{"id":"lonelymod:BrokenSpirit","name":"Broken Spirit","color":"Lonely_yellow","rarity":"Uncommon","type":"Skill","cost":"1","description":"Put (Add) a Primal on (to) ~~- top of  -~~ your draw pile (hand).\nGrant 2 Strength.\nGain 3 Frail.","mod":"LonelyMod"},{"id":"lonelymod:ChasingFantasies","name":"Chasing Fantasies","color":"Lonely_yellow","rarity":"Uncommon","type":"Skill","cost":"1","description":"lonelymod:Call lonelymod:Attack.\nlonelymod:Plan 4 (6).\nShuffle this card into your draw pile.","mod":"LonelyMod"},{"id":"lonelymod:Consideration","name":"Consideration","color":"Lonely_yellow","rarity":"Uncommon","type":"Skill","cost":"1","description":"lonelymod:Call lonelymod:Protect.\n (Grant 3 Vigor.)\nDraw 2 cards.","mod":"LonelyMod"},{"id":"lonelymod:DarkRitual","name":"Dark Ritual","color":"Lonely_yellow","rarity":"Uncommon","type":"Skill","cost":"1","description":"Exhaust 1 card.\nNext turn, gain Strength equal to double its cost (+ 1).","mod":"LonelyMod"},{"id":"lonelymod:EndlessOnslaught","name":"Endless Onslaught","color":"Lonely_yellow","rarity":"Uncommon","type":"Attack","cost":"1","description":"Deal 9 (10) damage.\nWhen you lonelymod:Plan, increase its damage by 3 (4) this combat.\nlonelymod:Return.","mod":"LonelyMod"},{"id":"lonelymod:FearTheBeast","name":"Fear The Beast","color":"Lonely_yellow","rarity":"Uncommon","type":"Power","cost":"1","description":"Whenever you lonelymod:Call lonelymod:Attack, gain 5 (7) Block.","mod":"LonelyMod"},{"id":"lonelymod:Fetch","name":"Fetch!","color":"Lonely_yellow","rarity":"Uncommon","type":"Attack","cost":"1","description":"Deal 8 (10) damage.\nApply 1 lonelymod:Target.\nNext time your lonelymod:Companion lonelymod:Attacks, grant 3 (4) Strength.","mod":"LonelyMod"},{"id":"lonelymod:FieryArrow","name":"Fiery Arrow","color":"Lonely_yellow","rarity":"Uncommon","type":"Attack","cost":"2","description":"Deal 12 (14) damage.\nAt the start of the enemy's next 3 turns, deal 6 (7) damage.","mod":"LonelyMod"},{"id":"lonelymod:Genius","name":"Genius","color":"Lonely_yellow","rarity":"Uncommon","type":"Skill","cost":"1","description":"lonelymod:Plan 3 (4).\nUpgrade selected cards for the rest of combat.\nGain 5 (7) lonelymod:Stamina.","mod":"LonelyMod"},{"id":"lonelymod:Improvise","name":"Improvise","color":"Lonely_yellow","rarity":"Uncommon","type":"Skill","cost":"0","description":"Choose 1 of 5 Skills of any color to add into your hand.\n (It costs 0 this turn.)\nExhaust.","mod":"LonelyMod"},{"id":"lonelymod:MultiShot","name":"Multi-Shot","color":"Lonely_yellow","rarity":"Uncommon","type":"Power","cost":"2","description":"Whenever you play an attack, deal 3 damage to a random enemy 2 (3) times.","mod":"LonelyMod"},{"id":"lonelymod:OnGuard","name":"On Guard","color":"Lonely_yellow","rarity":"Uncommon","type":"Skill","cost":"1","description":"Gain 4 (6) lonelymod:Stamina.\nIf any enemy intends to Attack, lonelymod:Call lonelymod:Protect and lonelymod:Return.","mod":"LonelyMod"},{"id":"lonelymod:OnTheHunt","name":"On The Hunt","color":"Lonely_yellow","rarity":"Uncommon","type":"Attack","cost":"1","description":"Deal 7 (10) damage.\nIf this deals 7 (10) or more unblocked damage, lonelymod:Call lonelymod:Attack and lonelymod:Return.","mod":"LonelyMod"},{"id":"lonelymod:Overcome","name":"Overcome","color":"Lonely_yellow","rarity":"Uncommon","type":"Power","cost":"1","description":" (Innate.)\nAt the end of your turn, gain 6 Block for every debuff you have.","mod":"LonelyMod"},{"id":"lonelymod:OverflowingQuiver","name":"Overflowing Quiver","color":"Lonely_yellow","rarity":"Uncommon","type":"Attack","cost":"0","description":"Ethereal.\nDeal 4 damage.\nShuffle a copy of this into your draw pile. (lonelymod:Return.)\n","mod":"LonelyMod"},{"id":"lonelymod:Overreaction","name":"Overreaction","color":"Lonely_yellow","rarity":"Uncommon","type":"Skill","cost":"0","description":"Ethereal.\nGain 3 (6) Block.\nDraw 2 cards.\nExhaust.","mod":"LonelyMod"},{"id":"lonelymod:PanicAttack","name":"Panic Attack","color":"Lonely_yellow","rarity":"Uncommon","type":"Attack","cost":"0","description":"Ethereal.\nDeal 4 (7) damage to a random enemy.\nGain [E] [E].\nExhaust.","mod":"LonelyMod"},{"id":"lonelymod:PinDown","name":"Pin Down","color":"Lonely_yellow","rarity":"Uncommon","type":"Skill","cost":"1","description":"Whenever you deal unblocked attack damage this turn, apply 1 lonelymod:Target (,)  (Vulnerable) and Vulnerable (Weak).","mod":"LonelyMod"},{"id":"lonelymod:PlanB","name":"Plan B","color":"Lonely_yellow","rarity":"Uncommon","type":"Power","cost":"1","description":"Whenever you lonelymod:Plan, gain 2 (3) Vigor for each card you didn't select.","mod":"LonelyMod"},{"id":"lonelymod:Prevail","name":"Prevail","color":"Lonely_yellow","rarity":"Uncommon","type":"Skill","cost":"2","description":"Gain 10 (12) Block.\nAt the start of your next 3 turns, gain 5 (6) Block.","mod":"LonelyMod"},{"id":"lonelymod:Recovery","name":"Recovery","color":"Lonely_yellow","rarity":"Uncommon","type":"Power","cost":"1 (0)","description":"Whenever you lonelymod:Call a lonelymod:Move while your lonelymod:Companion intends to lonelymod:Protect, gain [E].","mod":"LonelyMod"},{"id":"lonelymod:Relax","name":"Relax","color":"Lonely_yellow","rarity":"Uncommon","type":"Skill","cost":"1","description":"Draw 3 (4) cards.\nLose all your Block.\nFor every 5 Block lost, gain [E].","mod":"LonelyMod"},{"id":"lonelymod:SingleOut","name":"Single Out","color":"Lonely_yellow","rarity":"Uncommon","type":"Skill","cost":"1","description":"Apply 3 (4) lonelymod:Target.\nGain 6 (8) Block for every enemy in combat.","mod":"LonelyMod"},{"id":"lonelymod:Suppress","name":"Suppress","color":"Lonely_yellow","rarity":"Uncommon","type":"Attack","cost":"X","description":"Deal 5 (7) damage to a random enemy X times.\nGain 4 (6) Block X times.","mod":"LonelyMod"},{"id":"lonelymod:Teamwork","name":"Teamwork","color":"Lonely_yellow","rarity":"Uncommon","type":"Power","cost":"1","description":"Gain 1 (2) Dexterity.\nGrant 2 (3) Dexterity.","mod":"LonelyMod"},{"id":"lonelymod:TwistedChant","name":"Twisted Chant","color":"Lonely_yellow","rarity":"Uncommon","type":"Skill","cost":"0","description":"Ethereal.\nGain 3 (4) Strength this turn. Put a Dazed into your discard pile.\nlonelymod:Return.","mod":"LonelyMod"},{"id":"lonelymod:TwoStepsAhead","name":"Two Steps Ahead","color":"Lonely_yellow","rarity":"Uncommon","type":"Power","cost":"1","description":"Whenever you lonelymod:Plan, lonelymod:Plan 2 (3) more.","mod":"LonelyMod"},{"id":"lonelymod:Unwavering","name":"Unwavering","color":"Lonely_yellow","rarity":"Uncommon","type":"Skill","cost":"2","description":"Ethereal.\nGain 10 (13) plus ALL enemy's combined Strength in Block.\nlonelymod:Return.","mod":"LonelyMod"},{"id":"lonelymod:VentFrustration","name":"Vent Frustration","color":"Lonely_yellow","rarity":"Uncommon","type":"Attack","cost":"3","description":"Costs 1 less [E] for every lonelymod:Move you called this turn.\nDeal 7 (9) damage 3 times.","mod":"LonelyMod"},{"id":"lonelymod:WickedTalons","name":"Wicked Talons","color":"Lonely_yellow","rarity":"Uncommon","type":"Attack","cost":"2","description":"Deal 8 (10) damage twice.\nGain 2 Strength.\nLose 1 Dexterity.","mod":"LonelyMod"},{"id":"lonelymod:Abandon","name":"Abandon","color":"Lonely_yellow","rarity":"Rare","type":"Skill","cost":"1","description":"Ethereal.\nLose 10 (7) HP.\nRemove 1 card in your hand from your deck.\nExhaust.","mod":"LonelyMod"},{"id":"lonelymod:AccursedBeak","name":"Accursed Beak","color":"Lonely_yellow","rarity":"Rare","type":"Attack","cost":"1","description":"Deal 3 (5) damage.\nLose 1 Strength this turn.\nIf you have Strength, play this again.","mod":"LonelyMod"},{"id":"lonelymod:AgainstAllOdds","name":"Against All Odds","color":"Lonely_yellow","rarity":"Rare","type":"Attack","cost":"3","description":"Deal 26 (34) damage to ALL enemies.\nIf you have 20 HP or less, gain [E] [E] [E].","mod":"LonelyMod"},{"id":"lonelymod:Bravery","name":"Bravery","color":"Lonely_yellow","rarity":"Rare","type":"Power","cost":"2","description":"At the start of your turn, if ALL enemies intend to attack, gain 12 Vigor (and draw 1 card).","mod":"LonelyMod"},{"id":"lonelymod:Counterstrike","name":"Counterstrike","color":"Lonely_yellow","rarity":"Rare","type":"Attack","cost":"2 (1)","description":"Deal the same damage printed on this enemy's current intent.","mod":"LonelyMod"},{"id":"lonelymod:Cycle","name":"Cycle","color":"Lonely_yellow","rarity":"Rare","type":"Attack","cost":"0","description":"Deal 6 (9) damage.\nAll cards that will lonelymod:Return are lonelymod:Returned to your hand.","mod":"LonelyMod"},{"id":"lonelymod:DefyDeath","name":"Defy Death","color":"Lonely_yellow","rarity":"Rare","type":"Skill","cost":"2","description":"You cannot die this turn. Next turn,\ndraw 3 (4) cards and\ngain [E] [E] [E] ( [E]).\nExhaust.","mod":"LonelyMod"},{"id":"lonelymod:Desperation","name":"Desperation","color":"Lonely_yellow","rarity":"Rare","type":"Power","cost":"2","description":"At the end of your turn, play ~~- and exhaust  -~~ a random, non Ethereal card from your hand.","mod":"LonelyMod"},{"id":"lonelymod:ExponentialForce","name":"Exponential Force","color":"Lonely_yellow","rarity":"Rare","type":"Attack","cost":"2","description":"Deal 10 (13) damage.\nIf this doesn't kill an enemy, double its damage this combat.","mod":"LonelyMod"},{"id":"lonelymod:Frenzy","name":"Frenzy","color":"Lonely_yellow","rarity":"Rare","type":"Skill","cost":"X","description":"Your lonelymod:Companion lonelymod:Attacks X times on its next turn, and ignores lonelymod:Calls until then.\n~~- Exhaust. -~~ ","mod":"LonelyMod"},{"id":"lonelymod:GrandScheme","name":"Grand Scheme","color":"Lonely_yellow","rarity":"Rare","type":"Skill","cost":"1","description":" (Innate.)\nDiscard your draw pile.\nlonelymod:Plan your discard pile.\nExhaust.","mod":"LonelyMod"},{"id":"lonelymod:Lonely","name":"Lonely","color":"Lonely_yellow","rarity":"Rare","type":"Skill","cost":"3 (2)","description":"Choose a card to play: Bravery, Desperation, Resolve.\nEvery 16th card you play has no effect.","mod":"LonelyMod"},{"id":"lonelymod:Misery","name":"Misery","color":"Lonely_yellow","rarity":"Rare","type":"Skill","cost":"1","description":"Whenever you gain Block this turn,\ndeal 3 (5) damage to ALL enemies.\nGain 10 (12) Block.","mod":"LonelyMod"},{"id":"lonelymod:MuscleMemory","name":"Muscle Memory","color":"Lonely_yellow","rarity":"Rare","type":"Power","cost":"1 (0)","description":"Whenever your cards lonelymod:Return, gain [E].","mod":"LonelyMod"},{"id":"lonelymod:Omen","name":"Omen","color":"Lonely_yellow","rarity":"Rare","type":"Skill","cost":"0","description":"lonelymod:Summon lonelymod:Omen.\nlonelymod:Call lonelymod:Special.\nLose 4 (3) Strength.\nExhaust.","mod":"LonelyMod"},{"id":"lonelymod:Outburst","name":"Outburst","color":"Lonely_yellow","rarity":"Rare","type":"Skill","cost":"2","description":"Play (Choose) a (an) ~~- random  -~~ attack from your discard pile (.)\n (Play it) 3 times and exhaust it.\nExhaust.","mod":"LonelyMod"},{"id":"lonelymod:Primal","name":"Primal","color":"Lonely_yellow","rarity":"Rare","type":"Skill","cost":"1","description":" (Perform your Companion's) lonelymod: (Move.lonelymod:)\nCall lonelymod:Special.\nExhaust.","mod":"LonelyMod"},{"id":"lonelymod:Resolve","name":"Resolve","color":"Lonely_yellow","rarity":"Rare","type":"Power","cost":"2","description":"The first time you lose HP each turn, gain 2 Dexterity ( and 3 lonelymod:Plated lonelymod:Armor).","mod":"LonelyMod"},{"id":"lonelymod:WildForm","name":"Wild Form","color":"Lonely_yellow","rarity":"Rare","type":"Power","cost":"3","description":"~~- Ethereal. -~~\nWhenever you lonelymod:Call a lonelymod:Move, perform the previous lonelymod:Move.","mod":"LonelyMod"}],"relics":[{"id":"lonelymod:BonesStomach","name":"Bones' Stomach","tier":"Starter","pool":"Lonely_yellow","description":"At the start of combat, Summon Bones.","flavorText":"Given as a sign of trust, it has always been this empty.","mod":"LonelyMod"},{"id":"lonelymod:BoxOfTreats","name":"Box Of Treats","tier":"Common","pool":"Lonely_yellow","description":"Whenever a Companion is Summoned, Grant it 2 Strength and 1 Dexterity.","flavorText":"Every time you open this, another treat lies within.","mod":"LonelyMod"},{"id":"lonelymod:PaperDaug","name":"Paper Daug","tier":"Uncommon","pool":"Lonely_yellow","description":"Enemies with Target take 100% more damage from Companions rather than 50%.","flavorText":"Reminds you of Bones.","mod":"LonelyMod"},{"id":"lonelymod:ShortLeash","name":"Short Leash","tier":"Uncommon","pool":"Lonely_yellow","description":"At the start of combat, Call Protect.","flavorText":"Keep your friends close, and your enemies will be sure to keep their distance.","mod":"LonelyMod"},{"id":"lonelymod:Boomerang","name":"Boomerang","tier":"Rare","pool":"Lonely_yellow","description":"The first card you play each turn will Return to your hand next turn.","flavorText":"There seems to be no way to get rid of it.","mod":"LonelyMod"},{"id":"lonelymod:WorldMap","name":"World Map","tier":"Rare","pool":"Lonely_yellow","description":"At the end of your turn, after discarding your cards, Plan 4.","flavorText":"\"A well-documented map can do wonders for one's sense of direction.\" - The Architect","mod":"LonelyMod"},{"id":"lonelymod:GiftOfGod","name":"Gift of God","tier":"Boss","pool":"Lonely_yellow","description":"At the start of combat, shuffle a Godly Powers into your draw pile.","flavorText":"You may have this power, but not what you hoped to obtain through it.","mod":"LonelyMod"},{"id":"lonelymod:MeatsStomach","name":"Meat's Stomach","tier":"Boss","pool":"Lonely_yellow","description":"Replaces Bones' Stomach.\nAt the start of combat, Summon Meat.","flavorText":"You changed his name to something more fitting.","mod":"LonelyMod"},{"id":"lonelymod:Spyglass","name":"Spyglass","tier":"Shop","pool":"Lonely_yellow","description":"Whenever you Plan X while your discard pile is empty, Scry X + 3 instead.","flavorText":"The eyepiece is extremely cold.","mod":"LonelyMod"}],"potions":[{"id":"lonelymod:TargetPotion","name":"Target Potion","rarity":"Common","description":"Apply 5 Target.","mod":"LonelyMod"},{"id":"lonelymod:CannedMeat","name":"Canned Meat","rarity":"Uncommon","description":"Grant your Companion 3 Strength and 3 Dexterity.","mod":"LonelyMod"},{"id":"lonelymod:SpecialSauce","name":"Special Sauce","rarity":"Rare","description":"Your Companion performs its Special move immediately.","mod":"LonelyMod"}],"creatures":[{"id":"LonelyCharacter","name":"The Lonely","type":"Player","minHP":"70","maxHP":"78","minHPA":"63","maxHPA":"70","mod":"LonelyMod"}],"keywords":[{"name":"Plated Armor","description":"Creatures with Plated Armor gain Block at the end of their turn. Receiving unblocked attack damage reduces Plated Armor by 1.","mod":"LonelyMod"},{"name":"Attack","description":"Move: Focuses on dealing damage to enemies.","mod":"LonelyMod"},{"name":"Blirt","description":"A tinkering gremlin who loves all kinds of automatons. Her Moves are mainly focused on channeling orbs for you.","mod":"LonelyMod"},{"name":"Bones","description":"A loyal companion, with an insatiable appetite. Has many ways of improving its Attack Move.","mod":"LonelyMod"},{"name":"Companion Move","description":"Tell your Companion to perform this Move at the end of your turn.\nCalling another Move will override this Move.","mod":"LonelyMod"},{"name":"Dzil","description":"A cunning gremlin who loves killing things quietly. Play your Shiv cards on him to improve his next Attack.","mod":"LonelyMod"},{"name":"Default","description":"Move: The weakest Move.\nCompanions will default to performing this Move on their turn.","mod":"LonelyMod"},{"name":"Fring","description":"A sad gremlin with nothing but a spear. Give him your attention, and he can become a mighty warrior.","mod":"LonelyMod"},{"name":"Kharn","description":"A mostly insane gremlin, he has recognized your demonic powers and worships you for them. Gains Strength whenever you lose HP.","mod":"LonelyMod"},{"name":"Meat","description":"An immense beast, a formidable defense. It has lost neither its loyalty nor its appetite.","mod":"LonelyMod"},{"name":"Omen","description":"A powerful creature, able to destroy all who oppose you. Grant it Strength, and watch its Attack shred through your foes.","mod":"LonelyMod"},{"name":"Sowru","description":"A patient gremlin who eagerly awaits your command to attack. Her Protect Move will cause you to Enter Calm.","mod":"LonelyMod"},{"name":"Plan","description":"Look at the top X cards on your discard pile.\nYou may choose any of them to shuffle into your draw pile.","mod":"LonelyMod"},{"name":"Protect","description":"Move: Focuses on granting you Block or weakening enemies.","mod":"LonelyMod"},{"name":"Return","description":"Return this card to your hand at the start of next turn.","mod":"LonelyMod"},{"name":"Summon","description":"Replaces the current Companion with a new one. The first time a Move Calling card enters combat, a Gremlin Companion will automatically be Summoned.","mod":"LonelyMod"},{"name":"Special","description":"Move: The most powerful Move.\nEffects vary greatly between Companions.","mod":"LonelyMod"},{"name":"Stamina","description":"Your next Block Card gains additional Block.","mod":"LonelyMod"},{"name":"Target","description":"Targeted creatures take 50% more damage from Companions.\nCompanions will prioritize enemies with the most Target.","mod":"LonelyMod"}],"mods":[{"name":"LonelyMod","version":"1.1.3","authors":["zrgrush(Rushalisk), ocean"],"credits":"","description":"Adds The Lonely as a playable Character. Intended to be the logical complement to The Watcher as the 5th base game character.","mts_version":"3.30.0","sts_version":"12-18-2022","dependencies":["basemod","stslib"],"optional_dependencies":[]}]}